jenkins/__init__.py
jenkins/plugins.py
jenkins/version.py
python_jenkins-1.8.3.dist-info/AUTHORS
python_jenkins-1.8.3.dist-info/COPYING
python_jenkins-1.8.3.dist-info/METADATA
python_jenkins-1.8.3.dist-info/WHEEL
python_jenkins-1.8.3.dist-info/pbr.json
python_jenkins-1.8.3.dist-info/top_level.txt
python_jenkins-1.8.3.dist-info/RECORD
