Metadata-Version: 2.1
Name: python-jenkins
Version: 1.8.3
Summary: Python bindings for the remote Jenkins API
Home-page: https://opendev.org/jjb/python-jenkins
Author: Ken Conley
Author-email: kwc@willowgarage.com
Maintainer: Python-Jenkins Developers
Maintainer-email: python-jenkins-developers@lists.launchpad.net
License: BSD
Project-URL: Documentation, https://python-jenkins.readthedocs.io/
Classifier: Topic :: Utilities
Classifier: Intended Audience :: Developers
Classifier: Intended Audience :: Information Technology
Classifier: Intended Audience :: System Administrators
Classifier: Environment :: Console
Classifier: License :: OSI Approved :: BSD License
Classifier: Operating System :: OS Independent
Classifier: Programming Language :: Python
Classifier: Programming Language :: Python :: 3
Classifier: Programming Language :: Python :: 3.8
Classifier: Programming Language :: Python :: 3.9
Classifier: Programming Language :: Python :: 3.10
Classifier: Programming Language :: Python :: 3.11
Classifier: Programming Language :: Python :: 3.12
License-File: COPYING
Requires-Dist: pbr>=0.8.2
Requires-Dist: multi_key_dict
Requires-Dist: requests
